l2sl/__init__.py
l2sl/_forward.py
l2sl/_log_level.py
l2sl/_process.py
l2sl/_select.py
l2sl/_version.py
l2sl/py.typed
l2sl/_parsers/__init__.py
l2sl/_parsers/_core.py
l2sl/_parsers/_regexp.py
l2sl/_parsers/bokeh.py
l2sl/_parsers/httpx.py
l2sl/_parsers/panel.py
l2sl/_parsers/tornado.py
l2sl/_parsers/uvicorn.py
l2sl-0.3.0.dist-info/licenses/LICENSE
l2sl-0.3.0.dist-info/METADATA
l2sl-0.3.0.dist-info/WHEEL
l2sl-0.3.0.dist-info/top_level.txt
l2sl-0.3.0.dist-info/RECORD
