Metadata-Version: 2.4
Name: l2sl
Version: 0.3.0
Summary: logging to structured logging
Author-email: Philip Meier <github.pmeier@posteo.de>
License: BSD 3-Clause License
Project-URL: Repository, https://github.com/pmeier/l2sl
Project-URL: Documentation, https://l2sl.readthedocs.io/en/stable/
Classifier: Development Status :: 4 - Beta
Classifier: Programming Language :: Python :: 3.10
Classifier: Programming Language :: Python :: 3.11
Classifier: Programming Language :: Python :: 3.12
Classifier: Programming Language :: Python :: 3.13
Requires-Python: >=3.10
License-File: LICENSE
Requires-Dist: structlog>=25.2.0
Requires-Dist: typing-extensions; python_version < "3.11"
Dynamic: license-file
